data_merge/__init__.py
data_merge/file_merger.py
data_merge-0.1.2.dist-info/LICENSE
data_merge-0.1.2.dist-info/METADATA
data_merge-0.1.2.dist-info/WHEEL
data_merge-0.1.2.dist-info/top_level.txt
data_merge-0.1.2.dist-info/RECORD
