Metadata-Version: 2.1
Name: data-merge
Version: 0.1.2
Summary: Python package for merging Excel and CSV files
Author: Ojo Ilesanmi
Author-email: ojoilesanmi89@gmail.com
License-File: LICENSE
Requires-Dist: pandas
